---
layout: post
title: Java对象序列化
category: java技术
published: true
---
## 什么是Java对象序列化
Java平台允许我们在内存中创建可复用的Java对象，但一般情况下，只有当JVM处于运行时，这些对象才可能存在，即，这些对象的生命周期不会比JVM的生命周期更长。但在现实应用中，就可能要求在JVM停止运行之后能够保存(持久化)指定的对象，并在将来重新读取被保存的对象。Java对象序列化就能够帮助我们实现该功能。

使用Java对象序列化，在保存对象时，会把其状态保存为一组字节，在未来，再将这些字节组装成对象。必须注意地是，对象序列化保存的是对象的"状态"，即它的成员变量，因此，对象序列化不会关注类中的静态变量。

除了在持久化对象时会用到对象序列化之外，当使用RMI(远程方法调用)，或在网络中传递对象时，都会用到对象序列化。Java序列化API为处理对象序列化提供了一个标准机制，该API简单易用，在本文的后续章节中将会陆续讲到。
## 简单示例

在Java中，只要一个类实现了java.io.Serializable接口，那么它就可以被序列化。此处将创建一个可序列化的类Person，本文中的所有示例将围绕着该类或其修改版。

Gender类，是一个枚举类型，表示性别:

```java
public enum Gender {  
    MALE, FEMALE  
} 
```

Java每个枚举类型都会默认继承类java.lang.Enum，枚举类型对象都是默认可以被序列化的。

Person类，实现了Serializable接口，它包含三个字段：name，String类型；age，Integer类型；gender，Gender类型。另外，还重写该类的toString()方法，以方便打印Person实例中的内容。

```java
public class Person implements Serializable {  

    private String name = null;  
    private Integer age = null;  
    private Gender gender = null;  

    public Person() {  
        System.out.println("none-arg constructor");  
    }  
 
    public Person(String name, Integer age, Gender gender) {  
        System.out.println("arg constructor");  
        this.name = name;  
        this.age = age;  
        this.gender = gender;  
    }  
    // 省略getter/setter方法
} 
```

SimpleSerial，是一个简单的序列化程序，它先将一个Person对象保存到文件person.out中，然后再从该文件中读出被存储的Person对象，并打印该对象。

```java
public class SimpleSerial {  
 
    public static void main(String[] args) throws Exception {  
        File file = new File("person.out");  
 
        ObjectOutputStream oout = new ObjectOutputStream(new FileOutputStream(file));  
        Person person = new Person("John", 101, Gender.MALE);  
        oout.writeObject(person);  
        oout.close();  
 
        ObjectInputStream oin = new ObjectInputStream(new FileInputStream(file));  
        Object newPerson = oin.readObject(); // 没有强制转换到Person类型  
        oin.close();  
        System.out.println(newPerson);  
    }  
} 
```

上述程序的输出的结果为：

```java
arg constructor  
[John, 31, MALE] 
```

此时必须注意的是，当重新读取被保存的Person对象时，并没有调用Person的任何构造器，看起来就像是直接使用字节将Person对象还原出来的。

当Person对象被保存到person.out文件中之后，我们可以在其它地方去读取该文件以还原对象，但必须确保该读取程序的CLASSPATH中包含有Person.class(哪怕在读取Person对象时并没有显示地使用Person类，如上例所示)，否则会抛出ClassNotFoundException。

## Serializable的作用

为什么一个类实现了Serializable接口，它就可以被序列化呢？在上节的示例中，使用ObjectOutputStream来持久化对象，在该类中有如下代码：

```java
private void writeObject0(Object obj, boolean unshared) throws IOException {  
      ...
    if (obj instanceof String) {  
        writeString((String) obj, unshared);  
    } else if (cl.isArray()) {  
        writeArray(obj, desc, unshared);  
    } else if (obj instanceof Enum) {  
        writeEnum((Enum) obj, desc, unshared);  
    } else if (obj instanceof Serializable) {  
        writeOrdinaryObject(obj, desc, unshared);  
    } else {  
        if (extendedDebugInfo) {  
            throw new NotSerializableException(cl.getName() + "\n" 
                    + debugInfoStack.toString());  
        } else {  
            throw new NotSerializableException(cl.getName());  
        }  
    }  
    ...  
} 
```

从上述代码可知，如果被写对象的类型是String，或数组，或Enum，或Serializable，那么就可以对该对象进行序列化，否则将抛出NotSerializableException。

## 默认序列化机制

如果仅仅只是让某个类实现Serializable接口，而没有其它任何处理的话，则就是使用默认序列化机制。使用默认机制，在序列化对象时，不仅会序列化当前对象本身，还会对该对象引用的其它对象也进行序列化，同样地，这些其它对象引用的另外对象也将被序列化，以此类推。所以，如果一个对象包含的成员变量是容器类对象，而这些容器所含有的元素也是容器类对象，那么这个序列化的过程就会较复杂，开销也较大。

## 影响序列化

在现实应用中，有些时候不能使用默认序列化机制。比如，希望在序列化过程中忽略掉敏感数据，或者简化序列化过程。下面将介绍若干影响序列化的方法。

## transient关键字

当某个字段被声明为transient后，默认序列化机制就会忽略该字段。此处将Person类中的age字段声明为transient，如下所示，

```java
public class Person implements Serializable {  
    ...  
    transient private Integer age = null;  
    ...  
} 
```

再执行SimpleSerial应用程序，会有如下输出：

```java
arg constructor  
[John, null, MALE] 
```

可见，age字段未被序列化。

## writeObject()方法与readObject()方法

对于上述已被声明为transitive的字段age，除了将transitive关键字去掉之外，是否还有其它方法能使它再次可被序列化？方法之一就是在Person类中添加两个方法：writeObject()与readObject()，如下所示：

```java
public class Person implements Serializable {  
    ...  
    transient private Integer age = null;  
    ...  
 
    private void writeObject(ObjectOutputStream out) throws IOException {  
        out.defaultWriteObject();  
        out.writeInt(age);  
    }  
 
    private void readObject(ObjectInputStream in) throws IOException, ClassNotFoundException {  
        in.defaultReadObject();  
        age = in.readInt();  
    }  
} 
```

在writeObject()方法中会先调用ObjectOutputStream中的defaultWriteObject()方法，该方法会执行默认的序列化机制，如5.1节所述，此时会忽略掉age字段。然后再调用writeInt()方法显示地将age字段写入到ObjectOutputStream中。readObject()的作用则是针对对象的读取，其原理与writeObject()方法相同。再次执行SimpleSerial应用程序，则又会有如下输出：

arg constructor  
[John, 31, MALE] 
必须注意地是，writeObject()与readObject()都是private方法，那么它们是如何被调用的呢？毫无疑问，是使用反射。详情可以看看ObjectOutputStream中的writeSerialData方法，以及ObjectInputStream中的readSerialData方法。

## Externalizable接口

无论是使用transient关键字，还是使用writeObject()和readObject()方法，其实都是基于Serializable接口的序列化。JDK中提供了另一个序列化接口--Externalizable，使用该接口之后，之前基于Serializable接口的序列化机制就将失效。此时将Person类作如下修改，

```java
public class Person implements Externalizable {  
 
    private String name = null;  
 
    transient private Integer age = null;  
 
    private Gender gender = null;  
 
    public Person() {  
        System.out.println("none-arg constructor");  
    }  
 
    public Person(String name, Integer age, Gender gender) {  
        System.out.println("arg constructor");  
        this.name = name;  
        this.age = age;  
        this.gender = gender;  
    }  
 
    private void writeObject(ObjectOutputStream out) throws IOException {  
        out.defaultWriteObject();  
        out.writeInt(age);  
    }  
 
    private void readObject(ObjectInputStream in) throws IOException, ClassNotFoundException {  
        in.defaultReadObject();  
        age = in.readInt();  
    }  
 
    @Override 
    public void writeExternal(ObjectOutput out) throws IOException {  
 
    }  
 
    @Override 
    public void readExternal(ObjectInput in) throws IOException, ClassNotFoundException {  
 
    }  
    ...  
} 
```

此时再执行SimpleSerial程序之后会得到如下结果：

```java
arg constructor  
none-arg constructor  
[null, null, null] 
```

从该结果，一方面，可以看出Person对象中任何一个字段都没有被序列化。另一方面，如果细心的话，还可以发现这此次序列化过程调用了Person类的无参构造器。

Externalizable继承于Serializable，当使用该接口时，序列化的细节需要由程序员去完成。如上所示的代码，由于writeExternal()与readExternal()方法未作任何处理，那么该序列化行为将不会保存/读取任何一个字段。这也就是为什么输出结果中所有字段的值均为空。

另外，使用Externalizable进行序列化时，当读取对象时，会调用被序列化类的无参构造器去创建一个新的对象，然后再将被保存对象的字段的值分别填充到新对象中。这就是为什么在此次序列化过程中Person类的无参构造器会被调用。由于这个原因，实现Externalizable接口的类必须要提供一个无参的构造器，且它的访问权限为public。

对上述Person类进行进一步的修改，使其能够对name与age字段进行序列化，但忽略掉gender字段，如下代码所示：

```java
public class Person implements Externalizable {  
 
    private String name = null;  
 
    transient private Integer age = null;  
 
    private Gender gender = null;  
 
    public Person() {  
        System.out.println("none-arg constructor");  
    }  
 
    public Person(String name, Integer age, Gender gender) {  
        System.out.println("arg constructor");  
        this.name = name;  
        this.age = age;  
        this.gender = gender;  
    }  
 
    private void writeObject(ObjectOutputStream out) throws IOException {  
        out.defaultWriteObject();  
        out.writeInt(age);  
    }  
 
    private void readObject(ObjectInputStream in) throws IOException, ClassNotFoundException {  
        in.defaultReadObject();  
        age = in.readInt();  
    }  
 
    @Override 
    public void writeExternal(ObjectOutput out) throws IOException {  
        out.writeObject(name);  
        out.writeInt(age);  
    }  
 
    @Override 
    public void readExternal(ObjectInput in) throws IOException, ClassNotFoundException {  
        name = (String) in.readObject();  
        age = in.readInt();  
    }  
    ...  
} 
```

执行SimpleSerial之后会有如下结果：

```java
arg constructor  
none-arg constructor  
[John, 31, null] 
```

## readResolve()方法

当我们使用Singleton模式时，应该是期望某个类的实例应该是唯一的，但如果该类是可序列化的，那么情况可能略有不同。对Person类进行修改，使其实现Singleton模式，如下所示：

```java
public class Person implements Serializable {  
 
    private static class InstanceHolder {  
        private static final Person instatnce = new Person("John", 31, Gender.MALE);  
    }  
 
    public static Person getInstance() {  
        return InstanceHolder.instatnce;  
    }  
 
    private String name = null;  
 
    private Integer age = null;  
 
    private Gender gender = null;  
 
    private Person() {  
        System.out.println("none-arg constructor");  
    }  
 
    private Person(String name, Integer age, Gender gender) {  
        System.out.println("arg constructor");  
        this.name = name;  
        this.age = age;  
        this.gender = gender;  
    }  
    ...  
} 
```

同时要修改SimpleSerial应用，使得能够保存/获取上述单例对象，并进行对象相等性比较，如下代码所示：

```java
public class SimpleSerial {  
 
    public static void main(String[] args) throws Exception {  
        File file = new File("person.out");  
        ObjectOutputStream oout = new ObjectOutputStream(new FileOutputStream(file));  
        oout.writeObject(Person.getInstance()); // 保存单例对象  
        oout.close();  
 
        ObjectInputStream oin = new ObjectInputStream(new FileInputStream(file));  
        Object newPerson = oin.readObject();  
        oin.close();  
        System.out.println(newPerson);  
 
        System.out.println(Person.getInstance() == newPerson); // 将获取的对象与Person类中的单例对象进行相等性比较  
    }  
} 
```

执行上述应用程序后会得到如下结果：

```java
arg constructor  
[John, 31, MALE]  
false 
```

值得注意的是，从文件person.out中获取的Person对象与Person类中的单例对象并不相等。为了能在序列化过程仍能保持单例的特性，可以在Person类中添加一个readResolve()方法，在该方法中直接返回Person的单例对象，如下所示：

```java
public class Person implements Serializable {  
 
    private static class InstanceHolder {  
        private static final Person instatnce = new Person("John", 31, Gender.MALE);  
    }  
 
    public static Person getInstance() {  
        return InstanceHolder.instatnce;  
    }  
 
    private String name = null;  
 
    private Integer age = null;  
 
    private Gender gender = null;  
 
    private Person() {  
        System.out.println("none-arg constructor");  
    }  
 
    private Person(String name, Integer age, Gender gender) {  
        System.out.println("arg constructor");  
        this.name = name;  
        this.age = age;  
        this.gender = gender;  
    }  
 
    private Object readResolve() throws ObjectStreamException {  
        return InstanceHolder.instatnce;  
    }  
    ...  
} 
```

再次执行本节的SimpleSerial应用后将如下输出：

```java
arg constructor  
[John, 31, MALE]  
true 
```

无论是实现Serializable接口，或是Externalizable接口，当从I/O流中读取对象时，readResolve()方法都会被调用到。实际上就是用readResolve()中返回的对象直接替换在反序列化过程中创建的对象。  

## Enum类型的序列化问题
在Java中，对Enum类型的序列化与其他对象类型的序列化有所不同，例如

```java
public enum FruitEnum {  
    APPLE, ORAGE  
}  
```

编译查看字节码：

```vim
 > javac FruitEnum.java #编译源文件生成.class文件
 > ls
   FruitEnum.class FruitEnum.java
 > javap -verbose FruitEnum.class      
```

字节码如下：

```java
Classfile /Users/micx/JAVA_LAB/ENUM_LAB/FruitEnum.class
  Last modified Nov 8, 2014; size 781 bytes
  MD5 checksum 896d39f28645a81a7f85600e92636dab
  Compiled from "FruitEnum.java"
public final class FruitEnum extends java.lang.Enum<FruitEnum>
  Signature: #29                          // Ljava/lang/Enum<LFruitEnum;>;
  SourceFile: "FruitEnum.java"
  minor version: 0
  major version: 51
  flags: ACC_PUBLIC, ACC_FINAL, ACC_SUPER, ACC_ENUM
Constant pool:
   #1 = Fieldref           #4.#32         //  FruitEnum.$VALUES:[LFruitEnum;
   #2 = Methodref          #33.#34        //  "[LFruitEnum;".clone:()Ljava/lang/Object;
   #3 = Class              #17            //  "[LFruitEnum;"
   #4 = Class              #35            //  FruitEnum
   #5 = Methodref          #12.#36        //  java/lang/Enum.valueOf:(Ljava/lang/Class;Ljava/lang/String;)Ljava/lang/Enum;
   #6 = Methodref          #12.#37        //  java/lang/Enum."<init>":(Ljava/lang/String;I)V
   #7 = String             #13            //  APPLE
   #8 = Methodref          #4.#38         //  FruitEnum."<init>":(Ljava/lang/String;I)V
   #9 = Fieldref           #4.#39         //  FruitEnum.APPLE:LFruitEnum;
  #10 = String             #15            //  ORAGE
  #11 = Fieldref           #4.#40         //  FruitEnum.ORAGE:LFruitEnum;
  #12 = Class              #41            //  java/lang/Enum
  #13 = Utf8               APPLE
  #14 = Utf8               LFruitEnum;
  #15 = Utf8               ORAGE
  #16 = Utf8               $VALUES
  #17 = Utf8               [LFruitEnum;
  #18 = Utf8               values
  #19 = Utf8               ()[LFruitEnum;
  #20 = Utf8               Code
  #21 = Utf8               LineNumberTable
  #22 = Utf8               valueOf
  #23 = Utf8               (Ljava/lang/String;)LFruitEnum;
  #24 = Utf8               <init>
  #25 = Utf8               (Ljava/lang/String;I)V
  #26 = Utf8               Signature
  #27 = Utf8               ()V
  #28 = Utf8               <clinit>
  #29 = Utf8               Ljava/lang/Enum<LFruitEnum;>;
  #30 = Utf8               SourceFile
  #31 = Utf8               FruitEnum.java
  #32 = NameAndType        #16:#17        //  $VALUES:[LFruitEnum;
  #33 = Class              #17            //  "[LFruitEnum;"
  #34 = NameAndType        #42:#43        //  clone:()Ljava/lang/Object;
  #35 = Utf8               FruitEnum
  #36 = NameAndType        #22:#44        //  valueOf:(Ljava/lang/Class;Ljava/lang/String;)Ljava/lang/Enum;
  #37 = NameAndType        #24:#25        //  "<init>":(Ljava/lang/String;I)V
  #38 = NameAndType        #24:#25        //  "<init>":(Ljava/lang/String;I)V
  #39 = NameAndType        #13:#14        //  APPLE:LFruitEnum;
  #40 = NameAndType        #15:#14        //  ORAGE:LFruitEnum;
  #41 = Utf8               java/lang/Enum
  #42 = Utf8               clone
  #43 = Utf8               ()Ljava/lang/Object;
  #44 = Utf8               (Ljava/lang/Class;Ljava/lang/String;)Ljava/lang/Enum;
{
  public static final FruitEnum APPLE;
    flags: ACC_PUBLIC, ACC_STATIC, ACC_FINAL, ACC_ENUM

  public static final FruitEnum ORAGE;
    flags: ACC_PUBLIC, ACC_STATIC, ACC_FINAL, ACC_ENUM

  public static FruitEnum[] values();
    flags: ACC_PUBLIC, ACC_STATIC
    Code:
      stack=1, locals=0, args_size=0
         0: getstatic     #1                  // Field $VALUES:[LFruitEnum;
         3: invokevirtual #2                  // Method "[LFruitEnum;".clone:()Ljava/lang/Object;
         6: checkcast     #3                  // class "[LFruitEnum;"
         9: areturn       
      LineNumberTable:
        line 1: 0

  public static FruitEnum valueOf(java.lang.String);
    flags: ACC_PUBLIC, ACC_STATIC
    Code:
      stack=2, locals=1, args_size=1
         0: ldc_w         #4                  // class FruitEnum
         3: aload_0       
         4: invokestatic  #5                  // Method java/lang/Enum.valueOf:(Ljava/lang/Class;Ljava/lang/String;)Ljava/lang/Enum;
         7: checkcast     #4                  // class FruitEnum
        10: areturn       
      LineNumberTable:
        line 1: 0

  static {};
    flags: ACC_STATIC
    Code:
      stack=4, locals=0, args_size=0
         0: new           #4                  // class FruitEnum
         3: dup           
         4: ldc           #7                  // String APPLE
         6: iconst_0      
         7: invokespecial #8                  // Method "<init>":(Ljava/lang/String;I)V
        10: putstatic     #9                  // Field APPLE:LFruitEnum;
        13: new           #4                  // class FruitEnum
        16: dup           
        17: ldc           #10                 // String ORAGE
        19: iconst_1      
        20: invokespecial #8                  // Method "<init>":(Ljava/lang/String;I)V
        23: putstatic     #11                 // Field ORAGE:LFruitEnum;
        26: iconst_2      
        27: anewarray     #4                  // class FruitEnum
        30: dup           
        31: iconst_0      
        32: getstatic     #9                  // Field APPLE:LFruitEnum;
        35: aastore       
        36: dup           
        37: iconst_1      
        38: getstatic     #11                 // Field ORAGE:LFruitEnum;
        41: aastore       
        42: putstatic     #1                  // Field $VALUES:[LFruitEnum;
        45: return        
      LineNumberTable:
        line 2: 0
        line 1: 26
}
```

只显示方法：

```java
> javap  FruitEnum 

Compiled from "FruitEnum.java"
public final class FruitEnum extends java.lang.Enum<FruitEnum> {
  public static final FruitEnum APPLE;
  public static final FruitEnum ORAGE;
  public static FruitEnum[] values();
  public static FruitEnum valueOf(java.lang.String);
  static {};
}
```

编译后，编译器创建了一个类，这个类继承自 java.lang.Enum ，有两个公共的、静态的、被声明成final的属性，它们的类型就是我们定义的FruitEnum。

```java
public static final FruitEnum APPLE;
    flags: ACC_PUBLIC, ACC_STATIC, ACC_FINAL, ACC_ENUM

public static final FruitEnum ORAGE;
  flags: ACC_PUBLIC, ACC_STATIC, ACC_FINAL, ACC_ENUM
```

同时，编译器还生成了一个静态初始话器，就是字节码中static{};这一行下面的代码，其中的字节码创建了两个FruitEnum对象，同时分别赋值给APPLE和ORANGE这两个属性，调用的构造函数是定义在 java.lang.Enum中的protected Enum(String name, int ordinal)方法。在创建完成两个FruitEnum对象并且分别赋值给APPLE和ORIGIN之后，还创建了一个名叫ENUM$VALUES的数组，然后把APPLE和ORIGIN按照定义的顺序放如这个数组中。
 
除了这个静态初始化器之外，编译器还为我们生成了两个静态方法，values()和 valueOf(java.lang.String)方法。其中values()方法将ENUM$VALUES数组拷贝一份然后返回，而valueOf(java.lang.String)方法则会调用java.lang.Enum类中的valueOf方法，其作用是根据参数名找到对应的具体的枚举对象，如果找不到的话会抛出一个IllegalArgumentException异常。 

从上面的叙述可以看到，我们定义的枚举类型，经过编译器的处理最终会编程一个对象的定义，其中的枚举变量其实就是类的静态变量，因此Java中的枚举类型其实是具有很多对象的特性的，只不过平时我们都不太用到，比如枚举可以实现接口(不能继承)、定义方法等等。为了保证枚举类型像Java规范中所说的那样，每一个枚举类型极其定义的枚举变量在JVM中都是唯一的，在枚举类型的序列化和反序列化上，Java做了特殊的规定。原文如下(摘自Java的序列化规范)： 

### 引用

>Enum constants are serialized differently than ordinary serializable or externalizable objects. The serialized form of an enum constant consists solely of its name; field values of the constant are not present in the form. <font color="red">To serialize an enum constant, ObjectOutputStream writes the value returned by the enum constant's name method. To deserialize an enum constant, ObjectInputStream reads the constant name from the stream; the deserialized constant is then obtained by calling the java.lang.Enum.valueOf method, passing the constant's enum type along with the received constant name as arguments.</font> Like other serializable or externalizable objects, enum constants can function as the targets of back references appearing subsequently in the serialization stream. 
The process by which enum constants are serialized cannot be customized: any class-specific writeObject, readObject, readObjectNoData, writeReplace, and readResolve methods defined by enum types are ignored during serialization and deserialization. Similarly, any serialPersistentFields or serialVersionUID field declarations are also ignored--all enum types have a fixedserialVersionUID of 0L. Documenting serializable fields and data for enum types is unnecessary, since there is no variation in the type of data sent. 

在序列化的时候Java仅仅是将枚举对象的name属性输出到结果中，反序列化的时候则是通过java.lang.Enum的valueOf方法来根据名字查找枚举对象。同时，编译器是不允许任何对这种序列化机制的定制的，因此禁用了writeObject、readObject、readObjectNoData、writeReplace和readResolve等方法。下面我们来看看反序列化时候被调用的那个valueOf方法长什么样子。

```java

public static <T extends Enum<T>> T valueOf(Class<T> enumType, String name) {  
        T result = enumType.enumConstantDirectory().get(name);  
        if (result != null)  
            return result;  
        if (name == null)  
            throw new NullPointerException("Name is null");  
        throw new IllegalArgumentException(  
            "No enum const " + enumType +"." + name);  
}  
```

从代码中可以看到，代码会尝试从调用enumType这个Class对象的enumConstantDirectory()方法返回的map中获取名字为name的枚举对象，如果不存在就会抛出异常。再进一步跟到enumConstantDirectory()方法，就会发现到最后会以反射的方式调用enumType这个类型的values()静态方法，也就是上面我们看到的编译器为我们创建的那个方法，然后用返回结果填充enumType这个Class对象中的enumConstantDirectory属性。 

在了解了Java如何处理枚举的定义以及序列化和反序列化枚举类型之后，我们就需要在系统或者类库升级时，对其中定义的枚举类型多加注意，为了保持代码上的兼容性，如果我们定义的枚举类型有可能会被序列化保存(放到文件中、保存到数据库中，进入分布式内存缓存中)，那么我们是<font color="red">不能够删除原来枚举类型中定义的任何枚举对象的，否则程序在运行过程中，JVM就会抱怨找不到与某个名字对应的枚举对象了。</font>

另外，<font color="red">在远程方法调用过程中，如果我们发布的客户端接口返回值中使用了枚举类型，那么服务端在升级过程中就需要特别注意。如果在接口的返回结果的枚举类型中添加了新的枚举值，那就会导致仍然在使用老的客户端的那些应用出现调用失败的情况。</font>

因此，针对以上两种情况，应该尽量避免使用枚举，如果实在要用，也需要仔细设计，因为一旦用了枚举，有可能会给后期维护带来隐患。



